MANIFEST.in
README.rst
setup.py
pystun3_fix.egg-info/PKG-INFO
pystun3_fix.egg-info/SOURCES.txt
pystun3_fix.egg-info/dependency_links.txt
pystun3_fix.egg-info/entry_points.txt
pystun3_fix.egg-info/not-zip-safe
pystun3_fix.egg-info/top_level.txt
stun/__init__.py
stun/cli.py
tests/__init__.py
tests/test_cli.py