Metadata-Version: 1.1
Name: pystun3-fix
Version: 1.0.1
Summary: A Python STUN client for getting NAT type and external IP (RFC 3489)
Home-page: https://github.com/Narlim/pystun3
Author: Narlim (original authors: gaohawk, Justin Riley)
Author-email: wangweimingooo@gmail.com
License: MIT
Keywords: STUN NAT
Platform: UNKNOWN
Classifier: Development Status :: 4 - Beta
Classifier: License :: OSI Approved :: MIT License
Classifier: Programming Language :: Python :: 3
Classifier: Programming Language :: Python :: 3.8
Classifier: Topic :: Internet
Classifier: Topic :: System :: Networking :: Firewalls
